setup.py
pydht/__init__.py
pydht/driver.py
pydht2.egg-info/PKG-INFO
pydht2.egg-info/SOURCES.txt
pydht2.egg-info/dependency_links.txt
pydht2.egg-info/requires.txt
pydht2.egg-info/top_level.txt