Metadata-Version: 1.1
Name: pydht2
Version: 0.5.2
Summary: DHT 11 v.2 Temperature/Humidity GPIO driver for Raspberry PI.
Home-page: https://github.com/Sulverus/pydht
Author: Andrey Drozdov
Author-email: sulverus@gmail.com
License: http://www.apache.org/licenses/LICENSE-2.0
Download-URL: https://github.com/Sulverus/pydht
Platform: UNKNOWN
Classifier: Development Status :: 3 - Alpha
Classifier: Programming Language :: Python
Classifier: Programming Language :: Python :: 2.6
Classifier: Programming Language :: Python :: 2.7
Classifier: Environment :: Console
Classifier: Intended Audience :: Developers
Classifier: Intended Audience :: Education
Classifier: Intended Audience :: Science/Research
Classifier: License :: OSI Approved :: Apache Software License
Classifier: Topic :: Software Development
Classifier: Topic :: System :: Hardware :: Hardware Drivers
Classifier: Topic :: Software Development :: Libraries
Classifier: Topic :: Terminals
Classifier: Topic :: Utilities
